lucide/__init__.py
lucide/utils.py
lucide/icons/__init__.py
lucide/icons/a_arrow_down.py
lucide/icons/a_arrow_up.py
lucide/icons/a_large_small.py
lucide/icons/accessibility.py
lucide/icons/activity.py
lucide/icons/air_vent.py
lucide/icons/airplay.py
lucide/icons/alarm_clock.py
lucide/icons/alarm_clock_check.py
lucide/icons/alarm_clock_minus.py
lucide/icons/alarm_clock_off.py
lucide/icons/alarm_clock_plus.py
lucide/icons/alarm_smoke.py
lucide/icons/album.py
lucide/icons/align_center_horizontal.py
lucide/icons/align_center_vertical.py
lucide/icons/align_end_horizontal.py
lucide/icons/align_end_vertical.py
lucide/icons/align_horizontal_distribute_center.py
lucide/icons/align_horizontal_distribute_end.py
lucide/icons/align_horizontal_distribute_start.py
lucide/icons/align_horizontal_justify_center.py
lucide/icons/align_horizontal_justify_end.py
lucide/icons/align_horizontal_justify_start.py
lucide/icons/align_horizontal_space_around.py
lucide/icons/align_horizontal_space_between.py
lucide/icons/align_start_horizontal.py
lucide/icons/align_start_vertical.py
lucide/icons/align_vertical_distribute_center.py
lucide/icons/align_vertical_distribute_end.py
lucide/icons/align_vertical_distribute_start.py
lucide/icons/align_vertical_justify_center.py
lucide/icons/align_vertical_justify_end.py
lucide/icons/align_vertical_justify_start.py
lucide/icons/align_vertical_space_around.py
lucide/icons/align_vertical_space_between.py
lucide/icons/ambulance.py
lucide/icons/ampersand.py
lucide/icons/ampersands.py
lucide/icons/amphora.py
lucide/icons/anchor.py
lucide/icons/angry.py
lucide/icons/annoyed.py
lucide/icons/antenna.py
lucide/icons/anvil.py
lucide/icons/aperture.py
lucide/icons/app_window.py
lucide/icons/app_window_mac.py
lucide/icons/apple.py
lucide/icons/archive.py
lucide/icons/archive_restore.py
lucide/icons/archive_x.py
lucide/icons/armchair.py
lucide/icons/arrow_big_down.py
lucide/icons/arrow_big_down_dash.py
lucide/icons/arrow_big_left.py
lucide/icons/arrow_big_left_dash.py
lucide_py-0.3.5.dist-info/METADATA
lucide_py-0.3.5.dist-info/WHEEL
lucide_py-0.3.5.dist-info/RECORD
