Metadata-Version: 2.4
Name: lucide-py
Version: 0.3.5
Summary: A Lucide icon library package for Python applications
Author: Dotlabs Teams
License: MIT
Requires-Python: >=3.12
Requires-Dist: tagflow>=0.1.0
